[
    {"Name":"Rudrabhishek puja"},
    {"Name":"Satyanarayana Puja"},
    {"Name": "Aayusha Homa"},
    {"Name": "Navgraha Homa"},
    {"Name": "Gandmool Nakshatra Puja"},
    {"Name": "Ganesh Puja"},
    {"Name": "Annaprashan Puja"},
    {"Name": "Namkaran Puja"},
    {"Name": "Bhoomi Pujan"},
    {"Name": "Griha Pravesh"},
    {"Name": "Vivah"},
    {"Name": "Roka Ceremony"},
    {"Name": "Graha Shanti Puja"},
    {"Name": "Kuber Upasana/Lakshmi Kuber Homa"},
    {"Name": "Maha Lakshmi Puja"},
    {"Name": "Office Opening Puja"},
    {"Name": "Saraswati Puja"},
    {"Name": "Shuddhi Karan Puja"},
    {"Name": "Vishvakarma Puja"},
    {"Name": "Janeyu Sanskar (Upnayan)"},
    {"Name": "Maha Shivratri Puja"},
    {"Name": "Vechile Puja"},
    {"Name": "Karwa Chauth"},
    {"Name": "Vidhya Arambham"},
    {"Name": "Gauri Puja"},
    {"Name": "Punsavan Sanskar"},
    {"Name": "Ekadashi Vrat Udayapan Puja"},
    {"Name": "Sai Sandhya"},
    {"Name": "Chatt Puja"},
    {"Name": "Daseva-Teravhin Puja"},
    {"Name": "Lalitha Sasharnam Puja"},
    {"Name": "Solah Sombar Udapanan Puja"},
    {"Name": "Dhanvantri Homam"},
    {"Name": "Gyatri Mantra"},
    {"Name": "Gyatri mantra Jaap"},
    {"Name": "Mahamrityunjaya Jaap"},
    {"Name": "Santan Gopal Mantra Jaap"},
    {"Name": "Maha Ganpati Homa"},
    {"Name": "Durga Saptshati/Parayana/Chandi Homa/Durga Homa"},
    {"Name": "Lakshmi Narsimha Homa"},
    {"Name": "Akhand Ramayana Paath"},
    {"Name": "Sunderkand Paath"},
    {"Name": "Garud Puran Paath"},
    {"Name": "Hanuman Chalisa"},
    {"Name":"Navratri Kalash Sthapna"},
    {"Name":"Dhanteras Puja"},
    {"Name":"Dussera Puja"},
    {"Name":"Hartalika Teej Puja"},
    {"Name":"Holika Puja"},
    {"Name":"Vastu Shanti Puja"},
    {"Name":"Kumbh / Vishnu Vivah"},
    {"Name":"Tulsi Vivah"},
    {"Name":"Ark Vivah / Male"},
    {"Name":"Manglik Shanti"},
    {"Name":"Tripad Nakshtra Dosha Shanti Puja"},
    {"Name":"Manglik Shanti"},
    {"Name":"Manglik Shanti"},
    {"Name":"Manglik Shanti"},
    {"Name":"Narayana Bali"}
]